MANIFEST.in
README.md
run-uwsgi.sh
run-webapp.sh
setup.py
ch_frb_wview/__init__.py
ch_frb_wview/chime_frb_operations.py
ch_frb_wview/chime_frb_operations_interface.py
ch_frb_wview/chlog_database.py
ch_frb_wview/cnc_client.py
ch_frb_wview/cnc_ssh.py
ch_frb_wview/rpc_client.py
ch_frb_wview/webapp.py
ch_frb_wview.egg-info/PKG-INFO
ch_frb_wview.egg-info/SOURCES.txt
ch_frb_wview.egg-info/dependency_links.txt
ch_frb_wview.egg-info/requires.txt
ch_frb_wview.egg-info/top_level.txt
ch_frb_wview/config/l1_production_8beam_webapp.yaml
ch_frb_wview/databases/chime_frb_operations.sqlite3
ch_frb_wview/databases/log.sqlite3
ch_frb_wview/static/bootstrap-formhelpers.js
ch_frb_wview/static/bootstrap-formhelpers.min.css
ch_frb_wview/static/bootstrap.min.css
ch_frb_wview/static/bootstrap.min.js
ch_frb_wview/static/d3.min.js
ch_frb_wview/static/fullcalendar.css
ch_frb_wview/static/fullcalendar.min.js
ch_frb_wview/static/fullcalendar.print.css
ch_frb_wview/static/jquery.js
ch_frb_wview/static/moment.min.js
ch_frb_wview/templates/acq.html
ch_frb_wview/templates/acq_details.html
ch_frb_wview/templates/acq_history.html
ch_frb_wview/templates/diagnostics.html
ch_frb_wview/templates/home.html
ch_frb_wview/templates/index-new.html
ch_frb_wview/templates/index-newer.html
ch_frb_wview/templates/index.html
ch_frb_wview/templates/l0-node-map.html
ch_frb_wview/templates/l1-logs-recent.html
ch_frb_wview/templates/l1-logs-stdout.html
ch_frb_wview/templates/l1-service.html
ch_frb_wview/templates/layout.html
ch_frb_wview/templates/login.html
ch_frb_wview/templates/node-service.html
ch_frb_wview/templates/node-status.html
ch_frb_wview/templates/operations.html
ch_frb_wview/templates/packets-d3.html
ch_frb_wview/templates/packets-l0-d3.html
ch_frb_wview/templates/packets-l1-d3.html
ch_frb_wview/templates/sign_up_for_observations.html
ch_frb_wview/templates/strip-chart.js
ch_frb_wview/templates/includes/_messages.html
ch_frb_wview/templates/includes/_navbar.html