Metadata-Version: 1.0
Name: ch-frb-wview
Version: 1.0.0
Summary: Web Application to operate the FRB L1 system.
Home-page: https://github.com/CHIMEFRB/frb_monitoring.git
Author: Dustin Lang, Chitrang Patel
Author-email: chitrang.patel@mail.mcgill.ca
License: UNKNOWN
Platform: UNKNOWN
